[{
    "date": "2015-05-01",
    "pv": 1000,
    "uv": 455,
    "parts": 421
}, {
    "date": "2015-05-02",
    "pv": 2000,
    "uv": 1200,
    "parts": 422
}, {
    "date": "2015-05-03",
    "pv": 1010,
    "uv": 680,
    "parts": 418
}, {
    "date": "2015-05-04",
    "pv": 1020,
    "uv": 760,
    "parts": 413
}, {
    "date": "2015-05-05",
    "pv": 1100,
    "uv": 440,
    "parts": 411
}, {
    "date": "2015-05-06",
    "pv": 1080,
    "uv": 421,
    "parts": 405
}, {
    "date": "2015-05-07",
    "pv": 800,
    "uv": 300,
    "parts": 405
}, {
    "date": "2015-05-08",
    "pv": 1700,
    "uv": 890,
    "parts": 402
}, {
    "date": "2015-05-09",
    "pv": 2000,
    "uv": 1100,
    "parts": 406
}, {
    "date": "2015-05-10",
    "pv": 3300,
    "uv": 1600,
    "parts": 403
}, {
    "date": "2015-05-11",
    "pv": 1450,
    "uv": 600,
    "parts": 243
}, {
    "date": "2015-05-12",
    "pv": 3400,
    "uv": 1900,
    "parts": 249
}, {
    "date": "2015-05-13",
    "pv": 5400,
    "uv": 3000,
    "parts": 250
}, {
    "date": "2015-05-14",
    "pv": 4300,
    "uv": 2100,
    "parts": 255
}, {
    "date": "2015-05-15",
    "pv": 2100,
    "uv": 1900,
    "parts": 263
}, {
    "date": "2015-05-16",
    "pv": 2600,
    "uv": 1500,
    "parts": 263
}, {
    "date": "2015-05-17",
    "pv": 5600,
    "uv": 3700,
    "parts": 260
}, {
    "date": "2015-05-18",
    "pv": 7800,
    "uv": 5400,
    "parts": 256
}, {
    "date": "2015-05-19",
    "pv": 1000,
    "uv": 400,
    "parts": 256
}, {
    "date": "2015-05-20",
    "pv": 2300,
    "uv": 800,
    "parts": 253
}, {
    "date": "2015-05-21",
    "pv": 4000,
    "uv": 2400,
    "parts": 244
}]
